[
  {
    "name": "武汉",
    "updateTime": "2025-12-10T00:26+08:00",
    "temp": "9",
    "feelsLike": "9",
    "text": "雾",
    "windDir": "北风",
    "windScale": "0",
    "windSpeed": "0",
    "wind360": "0",
    "humidity": "89",
    "precip": "0.0",
    "pressure": "1019",
    "vis": "4",
    "dew": "6",
    "cloud": "10",
    "ai_briefing_zh": "武汉 夜间监测中，注意保暖",
    "ai_briefing_en": "武汉: Night watch, stay warm.",
    "alert": null
  },
  {
    "name": "武汉",
    "updateTime": "2025-12-10T01:08+08:00",
    "temp": "9",
    "feelsLike": "9",
    "text": "雾",
    "windDir": "北风",
    "windScale": "0",
    "windSpeed": "0",
    "wind360": "0",
    "humidity": "89",
    "precip": "0.0",
    "pressure": "1019",
    "vis": "5",
    "dew": "6",
    "cloud": "10",
    "ai_briefing_zh": "武汉 夜间监测中，注意保暖",
    "ai_briefing_en": "武汉: Night watch, stay warm.",
    "alert": null
  },
  {
    "name": "武汉",
    "updateTime": "2025-12-10T02:16+08:00",
    "temp": "9",
    "feelsLike": "9",
    "text": "雾",
    "windDir": "北风",
    "windScale": "0",
    "windSpeed": "0",
    "wind360": "0",
    "humidity": "91",
    "precip": "0.0",
    "pressure": "1019",
    "vis": "4",
    "dew": "8",
    "cloud": "10",
    "ai_briefing_zh": "武汉 夜间监测中，注意保暖",
    "ai_briefing_en": "武汉: Night watch, stay warm.",
    "alert": null
  }
]