[
  {
    "name": "大连",
    "updateTime": "2025-12-06T00:24+08:00",
    "temp": "6",
    "feelsLike": "0",
    "text": "多云",
    "windDir": "西南风",
    "windScale": "4",
    "windSpeed": "27",
    "wind360": "225",
    "humidity": "56",
    "precip": "0.0",
    "pressure": "1007",
    "vis": "20",
    "dew": "-2",
    "cloud": "10",
    "ai_briefing_zh": "大连 夜间监测中，注意保暖",
    "ai_briefing_en": "大连: Night watch, stay warm.",
    "alert": null
  },
  {
    "name": "大连",
    "updateTime": "2025-12-06T01:08+08:00",
    "temp": "6",
    "feelsLike": "0",
    "text": "多云",
    "windDir": "西南风",
    "windScale": "4",
    "windSpeed": "25",
    "wind360": "225",
    "humidity": "55",
    "precip": "0.0",
    "pressure": "1007",
    "vis": "13",
    "dew": "-2",
    "cloud": "10",
    "ai_briefing_zh": "大连 夜间监测中，注意保暖",
    "ai_briefing_en": "大连: Night watch, stay warm.",
    "alert": null
  },
  {
    "name": "大连",
    "updateTime": "2025-12-06T02:17+08:00",
    "temp": "6",
    "feelsLike": "-1",
    "text": "多云",
    "windDir": "西南风",
    "windScale": "5",
    "windSpeed": "29",
    "wind360": "225",
    "humidity": "60",
    "precip": "0.0",
    "pressure": "1006",
    "vis": "13",
    "dew": "-1",
    "cloud": "10",
    "ai_briefing_zh": "大连 夜间监测中，注意保暖",
    "ai_briefing_en": "大连: Night watch, stay warm.",
    "alert": null
  },
  {
    "name": "大连",
    "updateTime": "2025-12-06T03:10+08:00",
    "temp": "6",
    "feelsLike": "0",
    "text": "多云",
    "windDir": "西南风",
    "windScale": "4",
    "windSpeed": "24",
    "wind360": "225",
    "humidity": "61",
    "precip": "0.0",
    "pressure": "1005",
    "vis": "11",
    "dew": "-1",
    "cloud": "10",
    "ai_briefing_zh": "大连 夜间监测中，注意保暖",
    "ai_briefing_en": "大连: Night watch, stay warm.",
    "alert": null
  },
  {
    "name": "大连",
    "updateTime": "2025-12-06T04:16+08:00",
    "temp": "6",
    "feelsLike": "1",
    "text": "多云",
    "windDir": "西南风",
    "windScale": "4",
    "windSpeed": "21",
    "wind360": "225",
    "humidity": "63",
    "precip": "0.0",
    "pressure": "1005",
    "vis": "11",
    "dew": "0",
    "cloud": "10",
    "ai_briefing_zh": "大连 夜间监测中，注意保暖",
    "ai_briefing_en": "大连: Night watch, stay warm.",
    "alert": null
  },
  {
    "name": "大连",
    "updateTime": "2025-12-06T05:10+08:00",
    "temp": "6",
    "feelsLike": "2",
    "text": "多云",
    "windDir": "西南风",
    "windScale": "3",
    "windSpeed": "18",
    "wind360": "225",
    "humidity": "65",
    "precip": "0.0",
    "pressure": "1004",
    "vis": "10",
    "dew": "0",
    "cloud": "1",
    "ai_briefing_zh": "大连 夜间监测中，注意保暖",
    "ai_briefing_en": "大连: Night watch, stay warm.",
    "alert": null
  },
  {
    "name": "大连",
    "updateTime": "2025-12-06T06:16+08:00",
    "temp": "6",
    "feelsLike": "2",
    "text": "多云",
    "windDir": "西南风",
    "windScale": "3",
    "windSpeed": "16",
    "wind360": "225",
    "humidity": "62",
    "precip": "0.0",
    "pressure": "1004",
    "vis": "13",
    "dew": "0",
    "cloud": "10",
    "ai_briefing_zh": "大连 夜间监测中，注意保暖",
    "ai_briefing_en": "大连: Night watch, stay warm.",
    "alert": null
  },
  {
    "name": "大连",
    "updateTime": "2025-12-06T07:10+08:00",
    "temp": "6",
    "feelsLike": "2",
    "text": "多云",
    "windDir": "西南风",
    "windScale": "3",
    "windSpeed": "14",
    "wind360": "225",
    "humidity": "63",
    "precip": "0.0",
    "pressure": "1004",
    "vis": "11",
    "dew": "0",
    "cloud": "91",
    "ai_briefing_zh": "大连多云有风，体感 2℃，出门记得添衣哦。",
    "ai_briefing_en": "Dalian is cloudy and windy, feels 2℃. Stay warm!",
    "alert": null
  },
  {
    "name": "大连",
    "updateTime": "2025-12-06T09:24+08:00",
    "temp": "7",
    "feelsLike": "3",
    "text": "多云",
    "windDir": "西南风",
    "windScale": "3",
    "windSpeed": "14",
    "wind360": "225",
    "humidity": "58",
    "precip": "0.0",
    "pressure": "1004",
    "vis": "9",
    "dew": "0",
    "cloud": "91",
    "ai_briefing_zh": "大连 7℃，多云有风，体感较冷，注意防风保暖。",
    "ai_briefing_en": "Dalian 7℃, cloudy and windy. Feels quite cold, mind the wind and keep warm.",
    "alert": null
  }
]