[
  {
    "name": "南京",
    "updateTime": "2025-12-03T09:32+08:00",
    "temp": "5",
    "feelsLike": "0",
    "text": "晴",
    "windDir": "北风",
    "windScale": "3",
    "windSpeed": "17",
    "wind360": "0",
    "humidity": "47",
    "precip": "0.0",
    "pressure": "1029",
    "vis": "16",
    "dew": "-4",
    "cloud": "0",
    "ai_briefing": "AI ERROR 429",
    "ai_briefing_zh": "AI ERROR 429",
    "ai_briefing_en": "AI ERROR 429",
    "alert": null
  },
  {
    "name": "南京",
    "updateTime": "2025-12-03T11:08+08:00",
    "temp": "7",
    "feelsLike": "3",
    "text": "晴",
    "windDir": "西北风",
    "windScale": "3",
    "windSpeed": "12",
    "wind360": "315",
    "humidity": "39",
    "precip": "0.0",
    "pressure": "1029",
    "vis": "17",
    "dew": "-9",
    "cloud": "0",
    "ai_briefing": "AI ERROR 429",
    "ai_briefing_zh": "AI ERROR 429",
    "ai_briefing_en": "AI ERROR 429",
    "alert": null
  },
  {
    "name": "南京",
    "updateTime": "2025-12-03T12:23+08:00",
    "temp": "7",
    "feelsLike": "3",
    "text": "晴",
    "windDir": "西北风",
    "windScale": "3",
    "windSpeed": "13",
    "wind360": "315",
    "humidity": "39",
    "precip": "0.0",
    "pressure": "1029",
    "vis": "20",
    "dew": "-9",
    "cloud": "0",
    "ai_briefing": "AI ERROR 429",
    "ai_briefing_zh": "AI ERROR 429",
    "ai_briefing_en": "AI ERROR 429",
    "alert": null
  }
]